keras_htr/__init__.py
keras_htr/__version__.py
keras_htr/char_table.py
keras_htr/dataset_building.py
keras_htr/edit_distance.py
keras_htr/generators.py
keras_htr/models.py
keras_htr/segmentation.py
keras_htr-0.1.0.post1.dist-info/LICENSE
keras_htr-0.1.0.post1.dist-info/METADATA
keras_htr-0.1.0.post1.dist-info/WHEEL
keras_htr-0.1.0.post1.dist-info/top_level.txt
keras_htr-0.1.0.post1.dist-info/RECORD
