Metadata-Version: 2.1
Name: keras-htr
Version: 0.1.0.post1
Summary: A toolkit for developing handwritten text recognition (HTR) pipelines
Home-page: https://github.com/X-rayLaser/Keras-HTR
Author: Evgenii Dolotov
Author-email: supernovaprotocol@gmail.com
License: MIT
Platform: UNKNOWN
Classifier: Intended Audience :: Developers
Classifier: Programming Language :: Python :: 3.6
Classifier: License :: OSI Approved :: MIT License
Classifier: Operating System :: OS Independent
Requires-Dist: numpy
Requires-Dist: tensorflow (>=2)
Requires-Dist: Pillow
Requires-Dist: scipy
